MANIFEST.in
global-pkg.json
setup.py
configable/__init__.py
configable.egg-info/PKG-INFO
configable.egg-info/SOURCES.txt
configable.egg-info/dependency_links.txt
configable.egg-info/top_level.txt