Metadata-Version: 1.0
Name: configable
Version: 0.1.5
Summary: Don't repeat yourself. Configure everything.
Home-page: https://github.com/bauerca/configable
Author: Carl A. Bauer
Author-email: carl.a.bauer@gmail.com
License: MIT
Keywords: configuration
Platform: UNKNOWN
